pygit2/__init__.py
pygit2/_build.py
pygit2/_libgit2.abi3.so
pygit2/_pygit2.cpython-313-x86_64-linux-gnu.so
pygit2/_pygit2.pyi
pygit2/_run.py
pygit2/blame.py
pygit2/blob.py
pygit2/branches.py
pygit2/callbacks.py
pygit2/config.py
pygit2/credentials.py
pygit2/enums.py
pygit2/errors.py
pygit2/ffi.py
pygit2/filter.py
pygit2/index.py
pygit2/legacyenums.py
pygit2/options.py
pygit2/packbuilder.py
pygit2/py.typed
pygit2/references.py
pygit2/refspec.py
pygit2/remotes.py
pygit2/repository.py
pygit2/settings.py
pygit2/submodules.py
pygit2/transaction.py
pygit2/utils.py
pygit2/decl/attr.h
pygit2/decl/blame.h
pygit2/decl/buffer.h
pygit2/decl/callbacks.h
pygit2/decl/checkout.h
pygit2/decl/clone.h
pygit2/decl/commit.h
pygit2/decl/common.h
pygit2/decl/config.h
pygit2/decl/describe.h
pygit2/decl/diff.h
pygit2/decl/errors.h
pygit2/decl/graph.h
pygit2/decl/index.h
pygit2/decl/indexer.h
pygit2/decl/merge.h
pygit2/decl/net.h
pygit2/decl/oid.h
pygit2/decl/options.h
pygit2/decl/pack.h
pygit2/decl/proxy.h
pygit2/decl/refspec.h
pygit2/decl/remote.h
pygit2/decl/repository.h
pygit2/decl/revert.h
pygit2/decl/stash.h
pygit2/decl/strarray.h
pygit2/decl/submodule.h
pygit2/decl/transaction.h
pygit2/decl/transport.h
pygit2/decl/types.h
pygit2.libs/libcrypto-d9e0f080.so.3
pygit2.libs/libgit2-471ba634.so.1.9.2
pygit2.libs/libpcre-0dd207b5.so.1.2.10
pygit2.libs/libssh2-0c4447ac.so.1.0.1
pygit2.libs/libssl-e311de3d.so.3
pygit2-1.19.1.dist-info/METADATA
pygit2-1.19.1.dist-info/WHEEL
pygit2-1.19.1.dist-info/top_level.txt
pygit2-1.19.1.dist-info/RECORD
pygit2-1.19.1.dist-info/licenses/AUTHORS.md
pygit2-1.19.1.dist-info/licenses/COPYING
pygit2-1.19.1.dist-info/sboms/auditwheel.cdx.json
