Metadata-Version: 2.4
Name: pygit2
Version: 1.19.1
Summary: Python bindings for libgit2.
Home-page: https://github.com/libgit2/pygit2
Maintainer: J. David Ibáñez
Maintainer-email: jdavid.ibp@gmail.com
License: GPLv2 with linking exception
Project-URL: Documentation, https://www.pygit2.org/
Project-URL: Changelog, https://github.com/libgit2/pygit2/blob/master/CHANGELOG.md
Project-URL: Funding, https://github.com/sponsors/jdavid
Keywords: git
Classifier: Development Status :: 5 - Production/Stable
Classifier: Intended Audience :: Developers
Classifier: Programming Language :: Python
Classifier: Programming Language :: Python :: 3
Classifier: Programming Language :: Python :: 3.11
Classifier: Programming Language :: Python :: 3.12
Classifier: Programming Language :: Python :: 3.13
Classifier: Programming Language :: Python :: 3.14
Classifier: Programming Language :: Python :: Implementation :: PyPy
Classifier: Programming Language :: Python :: Implementation :: CPython
Classifier: Topic :: Software Development :: Version Control
Classifier: Typing :: Typed
Requires-Python: >=3.11
License-File: COPYING
License-File: AUTHORS.md
Requires-Dist: cffi>=2.0
Dynamic: classifier
Dynamic: description
Dynamic: description-content-type
Dynamic: home-page
Dynamic: keywords
Dynamic: license
Dynamic: license-file
Dynamic: maintainer
Dynamic: maintainer-email
Dynamic: project-url
Dynamic: requires-dist
Dynamic: requires-python
Dynamic: summary
